dorotheumypython/__init__.py
dorotheumypython/myfunction.py
dorotheumypython/wrapper.py
dorotheumypython/mymodule/__init__.py
dorotheumypython/mymodule/util.py
dorotheumypython-0.1.7.dist-info/METADATA
dorotheumypython-0.1.7.dist-info/WHEEL
dorotheumypython-0.1.7.dist-info/top_level.txt
dorotheumypython-0.1.7.dist-info/RECORD
