Metadata-Version: 2.1
Name: dorotheumypython
Version: 0.1.7
Summary: My first Python library
Home-page: UNKNOWN
Author: Dorotheu
Author-email: UNKNOWN
License: MIT
Platform: UNKNOWN
Requires-Dist: pandas
